elcrawl/__init__.py
elcrawl/cli/__init__.py
elcrawl/config/__init__.py
elcrawl/constants/__init__.py
elcrawl/core/__init__.py
elcrawl/core/client.py
elcrawl/core/config.py
elcrawl/core/log.py
elcrawl/core/request.py
elcrawl/db/__init__.py
elcrawl/db/es.py
elcrawl/db/kafka.py
elcrawl/db/mongo.py
elcrawl/db/sql.py
elcrawl/pipelines/__init__.py
elcrawl/utils/__init__.py
elcrawl/utils/config.py
elcrawl/utils/data.py
elcrawl/utils/scrapy.py
elcrawlsdk-1.0.0.dist-info/METADATA
elcrawlsdk-1.0.0.dist-info/WHEEL
elcrawlsdk-1.0.0.dist-info/entry_points.txt
elcrawlsdk-1.0.0.dist-info/top_level.txt
elcrawlsdk-1.0.0.dist-info/RECORD
