Metadata-Version: 2.1
Name: elcrawlsdk
Version: 1.0.0
Summary: Python SDK for elcrawl
Home-page: UNKNOWN
Author: jf
Author-email: jf@163.com
License: BSD-3-Clause
Platform: UNKNOWN
Classifier: Programming Language :: Python :: 3
Classifier: License :: OSI Approved :: BSD License
Classifier: Operating System :: OS Independent
Requires-Dist: Click (==7.0)
Requires-Dist: requests (==2.22.0)
Requires-Dist: prettytable (==0.7.2)
Requires-Dist: scrapy (==2.2.0)
Requires-Dist: pymongo (==3.10.1)
Requires-Dist: pymysql (==0.9.3)
Requires-Dist: psycopg2-binary (==2.8.5)
Requires-Dist: kafka-python (==2.0.1)
Requires-Dist: elasticsearch (==7.8.0)
Requires-Dist: pathspec (==0.8.0)
